README.txt
setup.py
cs/__init__.py
cs.i18n.egg-info/PKG-INFO
cs.i18n.egg-info/SOURCES.txt
cs.i18n.egg-info/dependency_links.txt
cs.i18n.egg-info/entry_points.txt
cs.i18n.egg-info/namespace_packages.txt
cs.i18n.egg-info/not-zip-safe
cs.i18n.egg-info/requires.txt
cs.i18n.egg-info/top_level.txt
cs/i18n/README.txt
cs/i18n/__init__.py
cs/i18n/configure.zcml
cs/i18n/interfaces.py
cs/i18n/version.txt
cs/i18n/Extensions/Install.py
cs/i18n/browser/__init__.py
cs/i18n/browser/configure.zcml
cs/i18n/browser/translatable.py
cs/i18n/browser/templates/translatablelanguageselector.pt
cs/i18n/profiles/default/browserlayer.xml
cs/i18n/profiles/default/portal_languages.xml
cs/i18n/tests/base.py
docs/HISTORY.txt
docs/INSTALL.txt
docs/LICENSE.GPL
docs/LICENSE.txt