Metadata-Version: 1.1
Name: cs.i18n
Version: 0.9
Summary: Some i18n customizations for Plone default language change forms
Home-page: http://code.codesyntax.com/private/cs.i18n
Author: Mikel Larreategi
Author-email: mlarreategi@codesyntax.com
License: GPL
Keywords: plone i18n
Platform: UNKNOWN
Classifier: Framework :: Plone
Classifier: Framework :: Zope2
Classifier: Framework :: Zope3
Classifier: Programming Language :: Python
Classifier: Topic :: Software Development :: Libraries :: Python Modules
